agents/__init__.py
agents/agents/__init__.py
agents/agents/gitchatbot/__init__.py
agents/agents/gitchatbot/agent.py
agents/agents/gitchatbot/config.py
agents/agents/gitchatbot/models.py
agents/agents/gitchatbot/prompts.py
agents/subagents/__init__.py
agents/subagents/changelog/__init__.py
agents/subagents/changelog/changelog_subagent.py
agents/subagents/changelog/models.py
agents/subagents/code_research/__init__.py
agents/subagents/code_research/code_research_agent.py
agents/subagents/code_research/models.py
agents/subagents/impact_analysis/__init__.py
agents/subagents/impact_analysis/impact_analysis_subagent.py
agents/subagents/impact_analysis/models.py
agents/tools/__init__.py
core/config.py
core/exceptions.py
core/log.py
core/message.py
core/project_config.py
core/prompts.py
core/storage.py
core/agents/__init__.py
core/agents/base.py
core/agents/context.py
core/agents/factory.py
core/agents/service.py
core/integrations/__init__.py
core/integrations/context_integration_loader.py
core/integrations/provider_registry.py
core/protocols/__init__.py
core/protocols/agent_protocols.py
core/protocols/message_consumer_protocols.py
core/protocols/provider_protocols.py
core/utils/progress_tracker.py
dev_agents-0.10.0.dist-info/licenses/LICENSE
entrypoints/__init__.py
entrypoints/main.py
entrypoints/agui_entrypoint/__init__.py
entrypoints/agui_entrypoint/agent_context.py
entrypoints/agui_entrypoint/message.py
entrypoints/agui_entrypoint/service.py
entrypoints/cli_entrypoint/__init__.py
entrypoints/cli_entrypoint/agent_context.py
entrypoints/cli_entrypoint/message.py
entrypoints/cli_entrypoint/service.py
entrypoints/slack_entrypoint/__init__.py
entrypoints/slack_entrypoint/agent_context.py
entrypoints/slack_entrypoint/agent_message_consumer.py
entrypoints/slack_entrypoint/service.py
entrypoints/slack_entrypoint/slack_bot_service.py
integrations/__init__.py
integrations/devops/__init__.py
integrations/devops/config.py
integrations/devops/mock_devops.py
integrations/devops/models.py
integrations/devops/provider.py
dev_agents-0.10.0.dist-info/METADATA
dev_agents-0.10.0.dist-info/WHEEL
dev_agents-0.10.0.dist-info/entry_points.txt
dev_agents-0.10.0.dist-info/top_level.txt
dev_agents-0.10.0.dist-info/RECORD
