Metadata-Version: 2.4
Name: dev-agents
Version: 0.10.0
Summary: AI Agents for Agile Dev Teams
Author-email: Dev Agents Team <dev@codeligence.com>, Juri Kuehn <juri@codeligence.com>
Maintainer-email: Juri Kuehn <juri@codeligence.com>
License-Expression: AGPL-3.0
Project-URL: Homepage, https://github.com/codeligence/dev-agents
Project-URL: Bug Tracker, https://github.com/codeligence/dev-agents/issues
Project-URL: Documentation, https://docs.dev-agents.ai
Project-URL: Repository, https://github.com/codeligence/dev-agents
Project-URL: Source Code, https://github.com/codeligence/dev-agents
Keywords: ai,agents,pydantic-ai,slack,azure-devops,automation,development,testing,impact-analysis,git,llm,chatbot
Classifier: Development Status :: 3 - Alpha
Classifier: Intended Audience :: Developers
Classifier: Intended Audience :: System Administrators
Classifier: Operating System :: OS Independent
Classifier: Programming Language :: Python :: 3
Classifier: Programming Language :: Python :: 3.11
Classifier: Programming Language :: Python :: 3.12
Classifier: Programming Language :: Python :: 3.13
Classifier: Topic :: Software Development :: Libraries :: Python Modules
Classifier: Topic :: Software Development :: Quality Assurance
Classifier: Topic :: Software Development :: Testing
Classifier: Topic :: Communications :: Chat
Classifier: Topic :: Scientific/Engineering :: Artificial Intelligence
Classifier: Typing :: Typed
Requires-Python: >=3.11
License-File: LICENSE
Requires-Dist: python-dotenv<2.0.0,>=1.0.1
Requires-Dist: pyyaml<7.0.0,>=6.0.2
Requires-Dist: dynaconf<4.0.0,>=3.2.11
Requires-Dist: jinja2<4.0.0,>=3.1.6
Requires-Dist: pydantic-ai~=1.0.5
Requires-Dist: beautifulsoup4~=4.13.5
Requires-Dist: fastapi~=0.116.1
Provides-Extra: slack
Requires-Dist: slack_sdk<4.0.0,>=3.19.5; extra == "slack"
Requires-Dist: markdown_to_mrkdwn~=0.2.0; extra == "slack"
Provides-Extra: azure
Requires-Dist: azure-devops<8.0.0,>=7.1.0b4; extra == "azure"
Provides-Extra: prod
Requires-Dist: dev-agents[azure,slack]; extra == "prod"
Provides-Extra: dev
Requires-Dist: pytest<9.0.0,>=8.4.1; extra == "dev"
Requires-Dist: pytest-asyncio<1.0.0,>=0.21.0; extra == "dev"
Requires-Dist: pytest-cov<7.0.0,>=4.1.0; extra == "dev"
Requires-Dist: pytest-mock<4.0.0,>=3.11.0; extra == "dev"
Requires-Dist: pytest-html<5.0.0,>=4.1.0; extra == "dev"
Requires-Dist: pytest-benchmark<6.0.0,>=4.0.0; extra == "dev"
Requires-Dist: pytest-xdist<4.0.0,>=3.3.0; extra == "dev"
Requires-Dist: black<25.0.0,>=23.0.0; extra == "dev"
Requires-Dist: isort<6.0.0,>=5.12.0; extra == "dev"
Requires-Dist: mypy<2.0.0,>=1.5.0; extra == "dev"
Requires-Dist: ruff<1.0.0,>=0.1.0; extra == "dev"
Requires-Dist: pre-commit<5.0.0,>=4.3.0; extra == "dev"
Requires-Dist: radon<7.0.0,>=6.0.1; extra == "dev"
Requires-Dist: xenon<1.0.0,>=0.9.0; extra == "dev"
Requires-Dist: vulture<3.0.0,>=2.10; extra == "dev"
Requires-Dist: mccabe<1.0.0,>=0.7.0; extra == "dev"
Requires-Dist: bandit[toml]<2.0.0,>=1.7.5; extra == "dev"
Requires-Dist: safety<4.0.0,>=3.0.0; extra == "dev"
Requires-Dist: pip-audit<3.0.0,>=2.6.0; extra == "dev"
Requires-Dist: docformatter<2.0.0,>=1.7.0; extra == "dev"
Requires-Dist: interrogate<2.0.0,>=1.5.0; extra == "dev"
Requires-Dist: coverage[toml]<8.0.0,>=7.3.0; extra == "dev"
Requires-Dist: coverage-badge<2.0.0,>=1.1.0; extra == "dev"
Requires-Dist: genbadge[coverage,tests]<2.0.0,>=1.1.0; extra == "dev"
Requires-Dist: diff-cover<10.0.0,>=8.0.0; extra == "dev"
Requires-Dist: pipdeptree<3.0.0,>=2.13.0; extra == "dev"
Requires-Dist: piprot<1.0.0,>=0.9.11; extra == "dev"
Requires-Dist: commitizen<4.0.0,>=3.25.0; extra == "dev"
Requires-Dist: gitpython<4.0.0,>=3.1.40; extra == "dev"
Requires-Dist: py-spy<1.0.0,>=0.3.14; extra == "dev"
Requires-Dist: memory-profiler<1.0.0,>=0.61.0; extra == "dev"
Requires-Dist: psutil<6.0.0,>=5.9.0; extra == "dev"
Provides-Extra: docs
Requires-Dist: mkdocs<2.0.0,>=1.6.1; extra == "docs"
Requires-Dist: mkdocs-material<10.0.0,>=9.6.17; extra == "docs"
Requires-Dist: mkdocstrings[python]<1.0.0,>=0.30.0; extra == "docs"
Requires-Dist: mkdocs-git-revision-date-localized-plugin<2.0.0,>=1.4.7; extra == "docs"
Requires-Dist: mkdocs-minify-plugin<1.0.0,>=0.8.0; extra == "docs"
Requires-Dist: mkdocs-social-plugin<1.0.0,>=0.1.0; extra == "docs"
Requires-Dist: pymdown-extensions<11.0.0,>=10.16.1; extra == "docs"
Requires-Dist: cairosvg<3.0.0,>=2.8.2; extra == "docs"
Requires-Dist: mike<3.0.0,>=2.1.3; extra == "docs"
Requires-Dist: griffe<2.0.0,>=1.12.1; extra == "docs"
Requires-Dist: mkdocs-autorefs<2.0.0,>=1.4.2; extra == "docs"
Requires-Dist: mkdocs-redirects<2.0.0,>=1.2.2; extra == "docs"
Requires-Dist: mkdocs-include-markdown-plugin<8.0.0,>=7.1.6; extra == "docs"
Provides-Extra: all
Requires-Dist: dev-agents[azure,dev,docs,slack]; extra == "all"
Dynamic: license-file
